lakehouse_mcp/__init__.py
lakehouse_mcp/__main__.py
lakehouse_mcp/config.py
lakehouse_mcp/server.py
lakehouse_mcp/client/__init__.py
lakehouse_mcp/client/watsonx.py
lakehouse_mcp/observability/__init__.py
lakehouse_mcp/observability/logging.py
lakehouse_mcp/observability/metrics.py
lakehouse_mcp/observability/tracing.py
lakehouse_mcp/tools/__init__.py
lakehouse_mcp/tools/catalog/__init__.py
lakehouse_mcp/tools/catalog/describe_table.py
lakehouse_mcp/tools/catalog/list_schemas.py
lakehouse_mcp/tools/catalog/list_tables.py
lakehouse_mcp/tools/engine/__init__.py
lakehouse_mcp/tools/engine/list_engines.py
lakehouse_mcp/tools/platform/__init__.py
lakehouse_mcp/tools/platform/get_instance_details.py
lakehouse_mcp/tools/query/__init__.py
lakehouse_mcp/tools/query/execute_select.py
ibm_watsonxdata_mcp_server-0.1.0.dist-info/METADATA
ibm_watsonxdata_mcp_server-0.1.0.dist-info/WHEEL
ibm_watsonxdata_mcp_server-0.1.0.dist-info/entry_points.txt
ibm_watsonxdata_mcp_server-0.1.0.dist-info/licenses/LICENSE
ibm_watsonxdata_mcp_server-0.1.0.dist-info/RECORD
