Metadata-Version: 2.4
Name: ibm-watsonxdata-mcp-server
Version: 0.1.0
Summary: Model Context Protocol (MCP) server for IBM watsonx.data - enables AI assistants to query and explore lakehouse data
Project-URL: Homepage, https://github.com/IBM/ibm-watsonxdata-mcp-server
Project-URL: Documentation, https://github.com/IBM/ibm-watsonxdata-mcp-server#readme
Project-URL: Repository, https://github.com/IBM/ibm-watsonxdata-mcp-server
Project-URL: Issues, https://github.com/IBM/ibm-watsonxdata-mcp-server/issues
Project-URL: Changelog, https://github.com/IBM/ibm-watsonxdata-mcp-server/blob/main/CHANGELOG.md
Author-email: IBM <noreply@ibm.com>
License: Apache-2.0
License-File: LICENSE
Keywords: ai,claude,fastmcp,ibm,lakehouse,llm,mcp,model-context-protocol,presto,spark,watsonx,watsonx-data
Classifier: Development Status :: 3 - Alpha
Classifier: Intended Audience :: Developers
Classifier: Intended Audience :: Information Technology
Classifier: License :: OSI Approved :: Apache Software License
Classifier: Operating System :: OS Independent
Classifier: Programming Language :: Python :: 3
Classifier: Programming Language :: Python :: 3.11
Classifier: Programming Language :: Python :: 3.12
Classifier: Programming Language :: Python :: 3.13
Classifier: Programming Language :: Python :: 3.14
Classifier: Topic :: Database
Classifier: Topic :: Scientific/Engineering :: Artificial Intelligence
Classifier: Topic :: Software Development :: Libraries :: Python Modules
Classifier: Typing :: Typed
Requires-Python: >=3.11
Requires-Dist: fastmcp>=2.3.0
Requires-Dist: filelock>=3.20.1
Requires-Dist: httpx>=0.27.0
Requires-Dist: ibm-cloud-sdk-core>=3.20.0
Requires-Dist: opentelemetry-api>=1.27.0
Requires-Dist: opentelemetry-instrumentation-httpx>=0.48b0
Requires-Dist: opentelemetry-sdk>=1.27.0
Requires-Dist: pydantic-settings>=2.0.0
Requires-Dist: pydantic>=2.0.0
Requires-Dist: structlog>=24.0.0
Requires-Dist: urllib3>=2.6.0
Provides-Extra: dev
Requires-Dist: mypy>=1.13.0; extra == 'dev'
Requires-Dist: pre-commit>=4.0.0; extra == 'dev'
Requires-Dist: pytest-asyncio>=0.24.0; extra == 'dev'
Requires-Dist: pytest-cov>=6.0.0; extra == 'dev'
Requires-Dist: pytest-env>=1.1.0; extra == 'dev'
Requires-Dist: pytest>=8.0.0; extra == 'dev'
Requires-Dist: respx>=0.21.0; extra == 'dev'
Requires-Dist: ruff>=0.7.0; extra == 'dev'
Requires-Dist: types-requests; extra == 'dev'
